[
  { "english": "Ahar", "divar": "ahar", "sheypoor": "ahar" },
  { "english": "Ajabshir", "divar": "ajabshir", "sheypoor": "ajabshir" },
  { "english": "Azarshahr", "divar": "azarshahr", "sheypoor": "azarshahr" },
  { "english": "bonab", "divar": "bonab", "sheypoor": "bonab" },
  { "english": "Bostan abad", "divar": "bostan-abad", "sheypoor": "bostan-abad" },
  { "english": "Hashtrud", "divar": "hashtrud", "sheypoor": "hashtrud" },
  { "english": "Heris", "divar": "heris", "sheypoor": "heris" },
  { "english": "Jolfa", "divar": "jolfa", "sheypoor": "jolfa" },
  { "english": "Kaleybar", "divar": "kaleybar", "sheypoor": "kaleybar" },
  { "english": "Malekan", "divar": "malekan", "sheypoor": "malekan" },
  { "english": "Maragheh", "divar": "maragheh", "sheypoor": "maragheh" },
  { "english": "Meyaneh", "divar": "meyaneh", "sheypoor": "meyaneh" },
  { "english": "Marand", "divar": "marand", "sheypoor": "marand" },
  { "english": "Osku", "divar": "osku", "sheypoor": "osku" },
  { "english": "Sarab", "divar": "sarab", "sheypoor": "sarab" },
  { "english": "Shabestar", "divar": "shabestar", "sheypoor": "shabestar" },
  { "english": "Tabriz", "divar": "tabriz", "sheypoor": "tabriz" },
  { "english": "Varzaqan", "divar": "varzaqan", "sheypoor": "varzaqan" },
  { "english": "Urmia", "divar": "urmia", "sheypoor": "urmia" },
  { "english": "Naqadeh", "divar": "naqadeh", "sheypoor": "naqadeh" },
  { "english": "Maku", "divar": "maku", "sheypoor": "maku" },
  { "english": "Takab", "divar": "takab", "sheypoor": "takab" },
  { "english": "Khoy", "divar": "khoy", "sheypoor": "khoy" },
  { "english": "Mahabad", "divar": "mahabad", "sheypoor": "mahabad" },
  { "english": "Sardasht", "divar": "sardasht", "sheypoor": "sardasht" },
  { "english": "Chaldoran", "divar": "chaldoran", "sheypoor": "chaldoran" },
  { "english": "Bukan", "divar": "bukan", "sheypoor": "bukan" },
  { "english": "Miandoab", "divar": "miandoab", "sheypoor": "miandoab" },
  { "english": "Salmas", "divar": "salmas", "sheypoor": "salmas" },
  {
    "english": "Shahin Dezh",
    "divar": "shahin-dej",
    "sheypoor": "shahin-dezh"
  },
  { "english": "Piranshahr", "divar": "piranshahr", "sheypoor": "piranshahr" },
  { "english": "Oshnavieh", "divar": "oshnavieh", "sheypoor": "oshnavieh" },
  { "english": "Chaypareh", "divar": "chaypareh", "sheypoor": "chaypareh" },
  { "english": "Poldasht", "divar": "poldasht", "sheypoor": "poldasht" },
  { "english": "Showt", "divar": "showt", "sheypoor": "showt" },
  { "english": "Ardabil", "divar": "ardabil", "sheypoor": "ardabil" },
  { "english": "Sareyn", "divar": "sarein", "sheypoor": "sareyn" },
  {
    "english": "Bileh Savar",
    "divar": "bileh-savar",
    "sheypoor": "bile-savar"
  },
  { "english": "Parsabad", "divar": "parsabad", "sheypoor": "parsabad" },
  { "english": "Khalkhal", "divar": "khalkhal", "sheypoor": "khalkhal" },
  {
    "english": "Meshgin Shahr",
    "divar": "meshgin-shahr",
    "sheypoor": "meshgin-shahr"
  },
  { "english": "Namin", "divar": "namin", "sheypoor": "namin" },
  { "english": "Nir", "divar": "nir", "sheypoor": "nir" },
  { "english": "Kowsar", "divar": "kowsar", "sheypoor": "kowsar" },
  { "english": "Germi", "divar": "germi", "sheypoor": "germi" },
  {
    "english": "Buin va Miandasht",
    "divar": "buin va miandasht",
    "sheypoor": "buin va miandasht"
  },
  { "english": "Mobarakeh", "divar": "mobarakeh", "sheypoor": "mobarakeh" },
  { "english": "Ardestan", "divar": "ardestan", "sheypoor": "ardestan" },
  {
    "english": "Khur and Biabanak",
    "divar": "khur and biabanak",
    "sheypoor": "khur and biabanak"
  },
  { "english": "Falavarjan", "divar": "falavarjan", "sheypoor": "falavarjan" },
  {
    "english": "Fereydunshahr",
    "divar": "fereydunshahr",
    "sheypoor": "fereydunshahr"
  },
  { "english": "Kashan", "divar": "kashan", "sheypoor": "kashan" },
  { "english": "Lenjan", "divar": "lenjan", "sheypoor": "lenjan" },
  { "english": "Golpayegan", "divar": "golpayegan", "sheypoor": "golpayegan" },
  { "english": "Faridan", "divar": "faridan", "sheypoor": "faridan" },
  { "english": "Nain", "divar": "nain", "sheypoor": "nain" },
  { "english": "Isfahan", "divar": "isfahan", "sheypoor": "isfahan" },
  { "english": "Najafabad", "divar": "najafabad", "sheypoor": "najaf-abad" },
  {
    "english": "Aran va Bidgol",
    "divar": "aran-va-bidgol",
    "sheypoor": "aran-va-bidgol"
  },
  { "english": "Chadegan", "divar": "chadegan", "sheypoor": "chadegan" },
  {
    "english": "Tiran",
    "divar": "tiran",
    "sheypoor": "tiran"
  },
  { "english": "Shahreza", "divar": "shahreza-city", "sheypoor": "shahreza" },
  { "english": "Semirom", "divar": "semirom", "sheypoor": "semirom" },
  {
    "english": "Khomeyni Shahr",
    "divar": "khomeyni-shahr",
    "sheypoor": "khomeyni-shahr"
  },
  { "english": "Dehaqan", "divar": "dehaqan", "sheypoor": "dehaqan" },
  { "english": "Natanz", "divar": "natanz", "sheypoor": "natanz" },
  { "english": "borkhar", "divar": "borkhar", "sheypoor": "borkhar" },
  {
    "english": "Shahin Shahr",
    "divar": "shahin-shahr",
    "sheypoor": "shahin-shahr"
  },
  { "english": "Khvansar", "divar": "khvansar", "sheypoor": "khvansar" },
  { "english": "Ilam", "divar": "ilam", "sheypoor": "ilam" },
  { "english": "Mehran", "divar": "mehran", "sheypoor": "mehran" },
  { "english": "Dehloran", "divar": "dehloran", "sheypoor": "dehloran" },
  { "english": "Abdanan", "divar": "abdanan", "sheypoor": "abdanan" },
  { "english": "Chardaval", "divar": "chardaval", "sheypoor": "chardaval" },
  {
    "english": "Darreh Shahr",
    "divar": "darreh-shahr",
    "sheypoor": "dareh-shahr"
  },
  { "english": "Eyvan", "divar": "eyvan", "sheypoor": "eyvan" },
  { "english": "Badreh", "divar": "badreh", "sheypoor": "badreh" },
  { "english": "Sirvan", "divar": "sirvan", "sheypoor": "sirvan" },
  { "english": "Malekshahi", "divar": "malekshahi", "sheypoor": "malekshahi" },
  { "english": "Asaluyeh", "divar": "asaluyeh", "sheypoor": "asaluyeh" },
  { "english": "Ganaveh", "divar": "ganaveh", "sheypoor": "ganaveh" },
  { "english": "Dashti", "divar": "dashti", "sheypoor": "dashti" },
  { "english": "Dashtestan", "divar": "dashtestan", "sheypoor": "dashtestan" },
  { "english": "Deyr", "divar": "deyr", "sheypoor": "deyr" },
  { "english": "Bushehr", "divar": "bushehr", "sheypoor": "bushehr" },
  { "english": "Kangan", "divar": "kangan", "sheypoor": "kangan" },
  { "english": "Tangestan", "divar": "tangestan", "sheypoor": "tangestan" },
  { "english": "Deylam", "divar": "deylam", "sheypoor": "deylam" },
  { "english": "Jam", "divar": "jam", "sheypoor": "jam" },
  { "english": "Qarchak", "divar": "qarchak", "sheypoor": "qarchak" },
  { "english": "Pardis", "divar": "pardis", "sheypoor": "pardis" },
  { "english": "Baharestan", "divar": "baharestan", "sheypoor": "baharestan" },
  { "english": "Shemiran", "divar": "shemiran", "sheypoor": "shemiran" },
  {
    "english": "Robat Karim",
    "divar": "robat-karim",
    "sheypoor": "robat-karim"
  },
  { "english": "FiruzkKuh", "divar": "firuzkkuh", "sheypoor": "firuzkkuh" },
  { "english": "Tehran", "divar": "tehran", "sheypoor": "tehran" },
  { "english": "Varamin", "divar": "varamin", "sheypoor": "varamin" },
  { "english": "Eslamshahr", "divar": "eslamshahr", "sheypoor": "eslamshahr" },
  { "english": "Ray", "divar": "ray", "sheypoor": "ray" },
  { "english": "Pakdasht", "divar": "pakdasht", "sheypoor": "pakdasht" },
  { "english": "Pishva", "divar": "pishva", "sheypoor": "pishva" },
  { "english": "Qods", "divar": "qods", "sheypoor": "qods" },
  { "english": "Malard", "divar": "malard", "sheypoor": "malard" },
  { "english": "Shahriar", "divar": "shahriar", "sheypoor": "shahriar" },
  { "english": "Damavand", "divar": "damavand", "sheypoor": "damavand" },
  { "english": "Bon", "divar": "bon", "sheypoor": "bon" },
  { "english": "Saman", "divar": "saman", "sheypoor": "saman" },
  { "english": "Kiar", "divar": "kiar", "sheypoor": "kiar" },
  { "english": "Borujen", "divar": "boroujen", "sheypoor": "borujen" },
  { "english": "Ardal", "divar": "ardal", "sheypoor": "ardal" },
  { "english": "Shahrekord", "divar": "shahrekord", "sheypoor": "shahrekord" },
  { "english": "Farsan", "divar": "farsan", "sheypoor": "farsan" },
  { "english": "Kuhrang", "divar": "kuhrang", "sheypoor": "kuhrang" },
  { "english": "Lordegan", "divar": "lordegan", "sheypoor": "lordegan" },
  { "english": "Davarzan", "divar": "davarzan", "sheypoor": "davarzan" },
  { "english": "Kalat", "divar": "kalat", "sheypoor": "kalat" },
  { "english": "Bardaskan", "divar": "bardaskan", "sheypoor": "bardaskan" },
  { "english": "Mashhad", "divar": "mashhad", "sheypoor": "mashhad" },
  { "english": "Nishapur", "divar": "nishapur", "sheypoor": "nishapur" },
  { "english": "Sabzevar", "divar": "sabzevar", "sheypoor": "sabzevar" },
  { "english": "Kashmar", "divar": "kashmar", "sheypoor": "kashmar" },
  { "english": "Gonabad", "divar": "gonabad", "sheypoor": "gonabad" },
  {
    "english": "Torbat Heydarieh",
    "divar": "torbat-heydariyeh",
    "sheypoor": "torbat-heydariyeh"
  },
  { "english": "Khvaf", "divar": "khvaf", "sheypoor": "khvaf" },
  { "english": "Torbat Jam", "divar": "torbat-jam", "sheypoor": "torbat-jam" },
  { "english": "Taybad", "divar": "taybad", "sheypoor": "taybad" },
  { "english": "Mahvelat", "divar": "mahvelat", "sheypoor": "mahvelat" },
  { "english": "Chenaran", "divar": "chenaran", "sheypoor": "chenaran" },
  { "english": "Dargaz", "divar": "dargaz", "sheypoor": "dargaz" },
  { "english": "Firuzeh", "divar": "firuzeh", "sheypoor": "firuzeh" },
  { "english": "Quchan", "divar": "quchan", "sheypoor": "quchan" },
  { "english": "Sarakhs", "divar": "sarakhs", "sheypoor": "sarakhs" },
  { "english": "Rashtkhvar", "divar": "rashtkhvar", "sheypoor": "rashtkhvar" },
  { "english": "Binaloud", "divar": "binaloud", "sheypoor": "binaloud" },
  { "english": "Zaveh", "divar": "zaveh", "sheypoor": "zaveh" },
  { "english": "Bajestan", "divar": "bajestan", "sheypoor": "bajestan" },
  { "english": "Bakharz", "divar": "bakharz", "sheypoor": "bakharz" },
  { "english": "Fariman", "divar": "fariman", "sheypoor": "fariman" },
  { "english": "Khalilabad", "divar": "khalilabad", "sheypoor": "khalilabad" },
  { "english": "Joghatai", "divar": "joghatai", "sheypoor": "joghatai" },
  { "english": "Khoshab", "divar": "khoshab", "sheypoor": "khoshab" },
  { "english": "Zirkuh", "divar": "zirkuh", "sheypoor": "zirkuh" },
  { "english": "Khusf", "divar": "khusf", "sheypoor": "khusf" },
  { "english": "Darmian", "divar": "darmian", "sheypoor": "darmian" },
  { "english": "Qaen", "divar": "qaen", "sheypoor": "qaen" },
  { "english": "Boshruyeh", "divar": "boshruyeh", "sheypoor": "boshruyeh" },
  { "english": "Ferdows", "divar": "ferdows", "sheypoor": "ferdows" },
  { "english": "Birjand", "divar": "birjand", "sheypoor": "birjand" },
  { "english": "Nehbandan", "divar": "nehbandan", "sheypoor": "nehbandan" },
  { "english": "Sarbisheh", "divar": "sarbisheh", "sheypoor": "sarbisheh" },
  { "english": "Sarayan", "divar": "sarayan", "sheypoor": "sarayan" },
  { "english": "Tabas", "divar": "tabas", "sheypoor": "tabas" },
  { "english": "Bojnurd", "divar": "bojnurd", "sheypoor": "bojnurd" },
  { "english": "Esfarayen", "divar": "esfarayen", "sheypoor": "esfarayen" },
  { "english": "Jajrom", "divar": "jajrom", "sheypoor": "jajrom" },
  { "english": "Shirvan", "divar": "shirvan", "sheypoor": "shirvan" },
  { "english": "Garmeh", "divar": "garmeh", "sheypoor": "garmeh" },
  { "english": "Faruj", "divar": "faruj", "sheypoor": "faruj" },
  { "english": "Karun", "divar": "karun", "sheypoor": "karun" },
  { "english": "Hamidiyeh", "divar": "hamidiyeh", "sheypoor": "hamidiyeh" },
  { "english": "Aghajari", "divar": "aghajari", "sheypoor": "aghajari" },
  { "english": "Shushtar", "divar": "shushtar", "sheypoor": "shushtar" },
  { "english": "Omidiyeh", "divar": "omidiyeh", "sheypoor": "omidiyeh" },
  { "english": "Gotvand", "divar": "gotvand", "sheypoor": "gotvand" },
  { "english": "Shadegan", "divar": "shadegan", "sheypoor": "shadegan" },
  { "english": "Dezful", "divar": "dezful", "sheypoor": "dezful" },
  { "english": "Ramshir", "divar": "ramshir", "sheypoor": "ramshir" },
  { "english": "Behbahan", "divar": "behbahan", "sheypoor": "behbahan" },
  { "english": "Bavi", "divar": "bavi", "sheypoor": "bavi" },
  { "english": "Andimeshk", "divar": "andimeshk", "sheypoor": "andimeshk" },
  { "english": "Ahvaz", "divar": "ahvaz", "sheypoor": "ahvaz" },
  { "english": "Andika", "divar": "andika", "sheypoor": "andika" },
  { "english": "Shush", "divar": "shush", "sheypoor": "shush" },
  { "english": "Abadan", "divar": "abadan", "sheypoor": "abadan" },
  { "english": "Hendijan", "divar": "hendijan", "sheypoor": "hendijan" },
  {
    "english": "Khorramshahr",
    "divar": "khorramshahr",
    "sheypoor": "khorramshahr"
  },
  {
    "english": "Masjed Soleyman",
    "divar": "masjed soleyman",
    "sheypoor": "masjed soleyman"
  },
  { "english": "Izeh", "divar": "izeh", "sheypoor": "izeh" },
  { "english": "Ramhormoz", "divar": "ramhormoz", "sheypoor": "ramhormoz" },
  { "english": "Bagh Malek", "divar": "bagh malek", "sheypoor": "bagh malek" },
  { "english": "Haftkel", "divar": "haftkel", "sheypoor": "haftkel" },
  { "english": "Hoveyzeh", "divar": "hoveyzeh", "sheypoor": "hoveyzeh" },
  { "english": "Mahshahr", "divar": "mahshahr", "sheypoor": "mahshahr" },
  { "english": "Lali", "divar": "lali", "sheypoor": "lali" },
  { "english": "Zanjan", "divar": "zanjan", "sheypoor": "zanjan" },
  { "english": "Abhar", "divar": "abhar", "sheypoor": "abhar" },
  {
    "english": "Khodabandeh",
    "divar": "khodabandeh",
    "sheypoor": "khodabandeh"
  },
  { "english": "Mahneshan", "divar": "mahneshan", "sheypoor": "mahneshan" },
  {
    "english": "Khorramdarreh",
    "divar": "khorramdarreh",
    "sheypoor": "khorramdarreh"
  },
  { "english": "Ijrud", "divar": "ijrud", "sheypoor": "ijrud" },
  { "english": "Tarom", "divar": "tarom", "sheypoor": "tarom" },
  { "english": "Soltaniyeh", "divar": "soltaniyeh", "sheypoor": "soltaniyeh" },
  { "english": "Semnan", "divar": "semnan", "sheypoor": "semnan" },
  { "english": "Shahrud", "divar": "shahrud", "sheypoor": "shahrud" },
  { "english": "Garmsar", "divar": "garmsar", "sheypoor": "garmsar" },
  { "english": "Sorkheh", "divar": "sorkheh", "sheypoor": "sorkheh" },
  { "english": "Damghan", "divar": "damghan", "sheypoor": "damghan" },
  { "english": "Aradan", "divar": "aradan", "sheypoor": "aradan" },
  { "english": "Mehdishahr", "divar": "mehdishahr", "sheypoor": "mehdishahr" },
  { "english": "Meyami", "divar": "meyami", "sheypoor": "meyami" },
  { "english": "Zahedan", "divar": "zahedan", "sheypoor": "zahedan" },
  { "english": "Bampur", "divar": "bampur", "sheypoor": "bampur" },
  { "english": "Chabahar", "divar": "chabahar", "sheypoor": "chabahar" },
  { "english": "Khash", "divar": "khash", "sheypoor": "khash" },
  { "english": "Saravan", "divar": "saravan", "sheypoor": "saravan" },
  { "english": "Zabol", "divar": "zabol", "sheypoor": "zabol" },
  { "english": "Sarbaz", "divar": "sarbaz", "sheypoor": "sarbaz" },
  { "english": "Qasr-Qand", "divar": "ghasrghand", "sheypoor": "qasreqand" },
  { "english": "Nik Shahr", "divar": "nik-shahr", "sheypoor": "nik-shahr" },
  { "english": "Konarak", "divar": "konarak", "sheypoor": "konarak" },
  { "english": "Iranshahr", "divar": "iranshahr", "sheypoor": "iranshahr" },
  { "english": "Zehak", "divar": "zehak", "sheypoor": "zehak" },
  { "english": "Mirjaveh", "divar": "mirjaveh", "sheypoor": "mirjaveh" },
  { "english": "Dalgan", "divar": "dalgan", "sheypoor": "dalgan" },
  { "english": "Hirmand", "divar": "hirmand", "sheypoor": "hirmand" },
  { "english": "Mehrestan", "divar": "mehrestan", "sheypoor": "mehrestan" },
  { "english": "Fanuj", "divar": "fanuj", "sheypoor": "fanuj" },
  { "english": "Hamoun", "divar": "hamoun", "sheypoor": "hamoun" },
  { "english": "Nimrouz", "divar": "nimrouz", "sheypoor": "nimrouz" },
  { "english": "Shiraz", "divar": "shiraz", "sheypoor": "shiraz" },
  { "english": "Eqlid", "divar": "eqlid", "sheypoor": "eqlid" },
  { "english": "Darab", "divar": "darab", "sheypoor": "darab" },
  { "english": "Fasa", "divar": "fasa", "sheypoor": "fasa" },
  { "english": "Marvdasht", "divar": "marvdasht", "sheypoor": "marvdasht" },
  { "english": "Khorrambid", "divar": "khorrambid", "sheypoor": "khorrambid" },
  { "english": "Abadeh", "divar": "abadeh", "sheypoor": "abadeh" },
  { "english": "Kazerun", "divar": "kazerun", "sheypoor": "kazerun" },
  { "english": "Gerash", "divar": "gerash", "sheypoor": "gerash" },
  { "english": "Mamasani", "divar": "mamasani", "sheypoor": "mamasani" },
  { "english": "Sepidan", "divar": "sepidan", "sheypoor": "sepidan" },
  { "english": "Larestan", "divar": "larestan", "sheypoor": "larestan" },
  { "english": "Firuzabad", "divar": "firuzabad", "sheypoor": "firuzabad" },
  { "english": "Jahrom", "divar": "jahrom", "sheypoor": "jahrom" },
  { "english": "Neyriz", "divar": "neyriz", "sheypoor": "neyriz" },
  { "english": "Estahban", "divar": "estahban", "sheypoor": "estahban" },
  { "english": "Lamerd", "divar": "lamerd", "sheypoor": "lamerd" },
  { "english": "Mohr", "divar": "mohr", "sheypoor": "mohr" },
  { "english": "Pasargad", "divar": "pasargad", "sheypoor": "pasargad" },
  { "english": "Arsanjan", "divar": "arsanjan", "sheypoor": "arsanjan" },
  { "english": "Rostam", "divar": "rostam", "sheypoor": "rostam" },
  { "english": "Farashband", "divar": "farashband", "sheypoor": "farashband" },
  { "english": "Sarvestan", "divar": "sarvestan", "sheypoor": "sarvestan" },
  {
    "english": "Zarrin Dasht",
    "divar": "zarrin dasht",
    "sheypoor": "zarrin dasht"
  },
  { "english": "Kavar", "divar": "kavar", "sheypoor": "kavar" },
  { "english": "Bavanat", "divar": "bavanat", "sheypoor": "bavanat" },
  { "english": "Kharameh", "divar": "kharameh", "sheypoor": "kharameh" },
  { "english": "Khonj", "divar": "khonj", "sheypoor": "khonj" },
  { "english": "Qazvin", "divar": "qazvin", "sheypoor": "qazvin" },
  { "english": "Takestan", "divar": "takestan", "sheypoor": "takestan" },
  { "english": "Abyek", "divar": "abyek", "sheypoor": "abyek" },
  { "english": "Buin Zahra", "divar": "buin zahra", "sheypoor": "buin zahra" },
  { "english": "Alborz", "divar": "alborz", "sheypoor": "alborz" },
  { "english": "Avaj", "divar": "avaj", "sheypoor": "avaj" },
  { "english": "Qom", "divar": "qom", "sheypoor": "qom" },
  { "english": "Taleqan", "divar": "taleqan", "sheypoor": "taleqan" },
  { "english": "Eshtehard", "divar": "eshtehard", "sheypoor": "eshtehard" },
  { "english": "Karaj", "divar": "karaj", "sheypoor": "karaj" },
  { "english": "Nazarabad", "divar": "nazarabad", "sheypoor": "nazarabad" },
  { "english": "Hashtgerd", "divar": "hashtgerd", "sheypoor": "hashtgerd" },
  { "english": "Fardis", "divar": "fardis", "sheypoor": "fardis" },
  { "english": "Sanandaj", "divar": "sanandaj", "sheypoor": "sanandaj" },
  {
    "english": "Divandarreh",
    "divar": "divandarreh",
    "sheypoor": "divandarreh"
  },
  { "english": "Baneh", "divar": "baneh", "sheypoor": "baneh" },
  { "english": "Bijar", "divar": "bijar", "sheypoor": "bijar" },
  { "english": "Saqqez", "divar": "saqqez", "sheypoor": "saqqez" },
  { "english": "Kamyaran", "divar": "kamyaran", "sheypoor": "kamyaran" },
  { "english": "Qorveh", "divar": "qorveh", "sheypoor": "qorveh" },
  { "english": "Marivan", "divar": "marivan", "sheypoor": "marivan" },
  { "english": "Sarvabad", "divar": "sarvabad", "sheypoor": "sarvabad" },
  { "english": "Dehgolan", "divar": "dehgolan", "sheypoor": "dehgolan" },
  { "english": "Kerman", "divar": "kerman", "sheypoor": "kerman" },
  { "english": "Ravar", "divar": "ravar", "sheypoor": "ravar" },
  {
    "english": "Shahr Babak",
    "divar": "shahr-babak",
    "sheypoor": "shahrebabak"
  },
  { "english": "Anar", "divar": "anar", "sheypoor": "anar" },
  { "english": "Kuhbanan", "divar": "kuhbanan", "sheypoor": "kuhbanan" },
  { "english": "Rafsanjan", "divar": "rafsanjan", "sheypoor": "rafsanjan" },
  { "english": "Sirjan", "divar": "sirjan", "sheypoor": "sirjan" },
  { "english": "Kahnuj", "divar": "kahnuj", "sheypoor": "kahnuj" },
  { "english": "Zarand", "divar": "zarand", "sheypoor": "zarand" },
  { "english": "Rigan", "divar": "rigan", "sheypoor": "rigan" },
  { "english": "Bam", "divar": "bam", "sheypoor": "bam" },
  { "english": "Jiroft", "divar": "jiroft", "sheypoor": "jiroft" },
  { "english": "Anbarabad", "divar": "anbarabad", "sheypoor": "anbarabad" },
  { "english": "Baft", "divar": "baft", "sheypoor": "baft" },
  { "english": "Arzuiyeh", "divar": "arzuiyeh", "sheypoor": "arzuiyeh" },
  { "english": "Bardsir", "divar": "bardsir", "sheypoor": "bardsir" },
  { "english": "Fahraj", "divar": "fahraj", "sheypoor": "fahraj" },
  { "english": "Faryab", "divar": "faryab", "sheypoor": "faryab" },
  { "english": "Manujan", "divar": "manujan", "sheypoor": "manujan" },
  { "english": "Narmashir", "divar": "narmashir", "sheypoor": "narmashir" },
  { "english": "Qaleh Ganj", "divar": "ghaleh-ganj", "sheypoor": "qaleh-ganj" },
  { "english": "Rabor", "divar": "rabor", "sheypoor": "rabor" },
  {
    "english": "Rudbar Jonubi",
    "divar": "rudbar-city",
    "sheypoor": "kerman-rudbar"
  },
  { "english": "Kermanshah", "divar": "kermanshah", "sheypoor": "kermanshah" },
  {
    "english": "Eslamabad-Gharb",
    "divar": "eslamabad-gharb",
    "sheypoor": "eslamabad-gharb"
  },
  {
    "english": "Sarpol-Zahab",
    "divar": "sarpol-zahab",
    "sheypoor": "sarpol-zahab"
  },
  { "english": "Kangavar", "divar": "kangavar", "sheypoor": "kangavar" },
  { "english": "Sonqor", "divar": "sonqor", "sheypoor": "sonqor" },
  {
    "english": "Ghasr-shirin",
    "divar": "ghasr-shirin",
    "sheypoor": "ghasr-shirin"
  },
  {
    "english": "Gilan-gharb",
    "divar": "gilan-gharb",
    "sheypoor": "gilan-gharb"
  },
  { "english": "Harsin", "divar": "harsin", "sheypoor": "harsin" },
  { "english": "Sahneh", "divar": "sahneh", "sheypoor": "sahneh" },
  { "english": "Paveh", "divar": "paveh", "sheypoor": "paveh" },
  { "english": "Javanrud", "divar": "javanrud", "sheypoor": "javanrud" },
  { "english": "Dalahu", "divar": "dalahu", "sheypoor": "dalahu" },
  { "english": "Ravansar", "divar": "ravansar", "sheypoor": "ravansar" },
  { "english": "Yasuj", "divar": "yasuj", "sheypoor": "yasuj" },
  { "english": "Gachsaran", "divar": "gachsaran", "sheypoor": "gachsaran" },
  { "english": "Dana", "divar": "dana", "sheypoor": "dana" },
  { "english": "Landeh", "divar": "landeh", "sheypoor": "landeh" },
  { "english": "Bahmai", "divar": "bahmai", "sheypoor": "bahmai" },
  { "english": "Basht", "divar": "basht", "sheypoor": "basht" },
  { "english": "Charam", "divar": "charam", "sheypoor": "charam" },
  { "english": "Gorgan", "divar": "gorgan", "sheypoor": "gorgan" },
  { "english": "Aqqala", "divar": "aq-qala", "sheypoor": "aq-qala" },
  {
    "english": "Gonbad-e Kavus",
    "divar": "gonbad-kavus",
    "sheypoor": "gonbad-kavus"
  },
  { "english": "Aliabad", "divar": "aliabad", "sheypoor": "aliabad" },
  { "english": "Minudasht", "divar": "minudasht", "sheypoor": "minudasht" },
  { "english": "Torkaman", "divar": "torkaman", "sheypoor": "torkaman" },
  { "english": "Kordkuy", "divar": "kordkuy", "sheypoor": "kordkuy" },
  { "english": "Bandar-Gaz", "divar": "bandar-gaz", "sheypoor": "bandar-gaz" },
  { "english": "Kalaleh", "divar": "kalaleh", "sheypoor": "kalaleh" },
  { "english": "Azadshahr", "divar": "azadshahr", "sheypoor": "azadshahr" },
  { "english": "Ramian", "divar": "ramian", "sheypoor": "ramian" },
  { "english": "Galikash", "divar": "galikash", "sheypoor": "galikash" },
  {
    "english": "Maraveh Tappeh",
    "divar": "maraveh tappeh",
    "sheypoor": "maraveh tappeh"
  },
  { "english": "Gomishan", "divar": "gomishan", "sheypoor": "gomishan" },
  { "english": "Rasht", "divar": "rasht", "sheypoor": "rasht" },
  { "english": "Langarud", "divar": "langarud", "sheypoor": "langarud" },
  { "english": "Rudsar", "divar": "rudsar", "sheypoor": "rudsar" },
  { "english": "Talesh", "divar": "talesh", "sheypoor": "talesh" },
  { "english": "Astara", "divar": "astara", "sheypoor": "astara" },
  {
    "english": "Astaneh-ye Ashrafiyeh",
    "divar": "astaneh-ashrafiyeh",
    "sheypoor": "astaneh-ashrafiyeh"
  },
  { "english": "Rudbar", "divar": "rudbar", "sheypoor": "gilan-rudbar" },
  { "english": "Fuman", "divar": "fuman", "sheypoor": "fuman" },
  { "english": "Someh Sara", "divar": "someh-sara", "sheypoor": "someh-sara" },
  {
    "english": "Bandar Anzali",
    "divar": "bandar-anzali",
    "sheypoor": "bandar-anzali"
  },
  {
    "english": "Rezvanshahr",
    "divar": "rezvanshahr",
    "sheypoor": "rezvanshahr"
  },
  { "english": "Masal", "divar": "masal", "sheypoor": "masal" },
  { "english": "Shaft", "divar": "shaft", "sheypoor": "shaft" },
  { "english": "Siahkal", "divar": "siahkal", "sheypoor": "siahkal" },
  { "english": "Amlash", "divar": "amlash", "sheypoor": "amlash" },
  { "english": "Lahijan", "divar": "lahijan", "sheypoor": "lahijan" },
  {
    "english": "Khorramabad",
    "divar": "khorramabad",
    "sheypoor": "lorestan-khorram-abad"
  },
  { "english": "Delfan", "divar": "delfan", "sheypoor": "delfan" },
  { "english": "Borujerd", "divar": "borujerd", "sheypoor": "borujerd" },
  { "english": "Dorud", "divar": "dorud", "sheypoor": "dorud" },
  { "english": "Aligudarz", "divar": "aligudarz", "sheypoor": "aligudarz" },
  { "english": "Azna", "divar": "azna", "sheypoor": "azna" },
  { "english": "Kuhdasht", "divar": "kuhdasht", "sheypoor": "kuhdasht" },
  { "english": "Selseleh", "divar": "selseleh", "sheypoor": "selseleh" },
  {
    "english": "Pol-Dokhtar",
    "divar": "pol-dokhtar",
    "sheypoor": "pol-dokhtar"
  },
  { "english": "Dowreh", "divar": "dowreh", "sheypoor": "dowreh" },
  { "english": "Rumeshkhan", "divar": "rumeshkhan", "sheypoor": "rumeshkhan" },
  { "english": "Sari", "divar": "sari", "sheypoor": "sari" },
  { "english": "Amol", "divar": "amol", "sheypoor": "amol" },
  { "english": "Babol", "divar": "babol", "sheypoor": "babol" },
  { "english": "Babolsar", "divar": "babolsar", "sheypoor": "babolsar" },
  { "english": "Behshahr", "divar": "behshahr", "sheypoor": "behshahr" },
  { "english": "Tonekabon", "divar": "tonekabon", "sheypoor": "tonekabon" },
  { "english": "Juybar", "divar": "juybar", "sheypoor": "juybar" },
  { "english": "Chalus", "divar": "chalus", "sheypoor": "chalus" },
  { "english": "Ramsar", "divar": "ramsar", "sheypoor": "ramsar" },
  { "english": "Savadkuh", "divar": "savadkuh", "sheypoor": "savadkuh" },
  { "english": "Qaemshahr", "divar": "qaemshahr", "sheypoor": "qaem-shahr" },
  { "english": "Neka", "divar": "neka", "sheypoor": "neka" },
  { "english": "Nur", "divar": "nur", "sheypoor": "nur" },
  { "english": "Nowshahr", "divar": "nowshahr", "sheypoor": "nowshahr" },
  { "english": "Mahmudabad", "divar": "mahmudabad", "sheypoor": "mahmudabad" },
  {
    "english": "Fereydunkenar",
    "divar": "fereydunkenar",
    "sheypoor": "fereydunkenar"
  },
  { "english": "Abbasabad", "divar": "abbasabad", "sheypoor": "abbasabad" },
  { "english": "Galugah", "divar": "galugah", "sheypoor": "galugah" },
  { "english": "Miandorud", "divar": "miandorud", "sheypoor": "miandorud" },
  { "english": "Simorgh", "divar": "simorgh", "sheypoor": "simorgh" },
  { "english": "Kelardasht", "divar": "kelardasht", "sheypoor": "kelardasht" },
  {
    "english": "Savadkooh Shomali",
    "divar": "savadkooh shomali",
    "sheypoor": "savadkooh shomali"
  },
  { "english": "Arak", "divar": "arak", "sheypoor": "arak" },
  { "english": "Ashtian", "divar": "ashtian", "sheypoor": "ashtian" },
  { "english": "Tafresh", "divar": "tafresh", "sheypoor": "tafresh" },
  { "english": "Khomeyn", "divar": "khomeyn", "sheypoor": "khomeyn" },
  { "english": "Delijan", "divar": "delijan", "sheypoor": "delijan" },
  { "english": "Saveh", "divar": "saveh", "sheypoor": "saveh" },
  { "english": "Zarandieh", "divar": "zarandieh", "sheypoor": "zarandieh" },
  { "english": "Mahallat", "divar": "mahallat", "sheypoor": "mahallat" },
  { "english": "Shazand", "divar": "shazand", "sheypoor": "shazand" },
  { "english": "Farahan", "divar": "farahan", "sheypoor": "farahan" },
  { "english": "Khondab", "divar": "khondab", "sheypoor": "khondab" },
  { "english": "Komijan", "divar": "komijan", "sheypoor": "komijan" },
  {
    "english": "Bandar Abbas",
    "divar": "bandar-abbas",
    "sheypoor": "bandar-abbas"
  },
  { "english": "Qeshm", "divar": "qeshm", "sheypoor": "qeshm" },
  {
    "english": "Bandar Lengeh",
    "divar": "bandar lengeh",
    "sheypoor": "bandar lengeh"
  },
  { "english": "Bastak", "divar": "bastak", "sheypoor": "bastak" },
  {
    "english": "Hajjiabad Hormozgan",
    "divar": "hajjiabad hormozgan",
    "sheypoor": "hajjiabad hormozgan"
  },
  { "english": "Rudan", "divar": "rudan", "sheypoor": "rudan" },
  { "english": "Minab", "divar": "minab", "sheypoor": "minab" },
  { "english": "Abumusa", "divar": "abumusa", "sheypoor": "abumusa" },
  { "english": "Jask", "divar": "jask", "sheypoor": "jask" },
  { "english": "Khamir", "divar": "khamir", "sheypoor": "khamir" },
  { "english": "Parsian", "divar": "parsian", "sheypoor": "parsian" },
  { "english": "Bashagard", "divar": "bashagard", "sheypoor": "bashagard" },
  { "english": "Sirik", "divar": "sirik", "sheypoor": "sirik" },
  { "english": "Hajjiabad", "divar": "hajjiabad", "sheypoor": "hajjiabad" },
  { "english": "Hamadan", "divar": "hamadan", "sheypoor": "hamadan" },
  { "english": "Malayer", "divar": "malayer", "sheypoor": "malayer" },
  { "english": "Tuyserkan", "divar": "tuyserkan", "sheypoor": "tuyserkan" },
  { "english": "Nahavand", "divar": "nahavand", "sheypoor": "nahavand" },
  {
    "english": "Kabudarahang",
    "divar": "kabudarahang",
    "sheypoor": "kabudarahang"
  },
  { "english": "Razan", "divar": "razan", "sheypoor": "razan" },
  { "english": "Asadabad", "divar": "asadabad", "sheypoor": "asadabad" },
  { "english": "Bahar", "divar": "bahar", "sheypoor": "bahar" },
  { "english": "Famenin", "divar": "famenin", "sheypoor": "famenin" },
  { "english": "Yazd", "divar": "yazd", "sheypoor": "yazd" },
  { "english": "Taft", "divar": "taft", "sheypoor": "taft" },
  { "english": "Ardakan", "divar": "ardakan", "sheypoor": "ardakan" },
  { "english": "Abarkuh", "divar": "abarkuh", "sheypoor": "abarkuh" },
  { "english": "Meybod", "divar": "meybod", "sheypoor": "meybod" },
  { "english": "Bafq", "divar": "bafq", "sheypoor": "bafq" },
  { "english": "Saduq", "divar": "saduq", "sheypoor": "saduq" },
  { "english": "Mehriz", "divar": "mehriz", "sheypoor": "mehriz" },
  { "english": "Khatam", "divar": "khatam", "sheypoor": "khatam" }
]
